odoo/addons/l10n_ch_isr_payment_grouping/README.rst
odoo/addons/l10n_ch_isr_payment_grouping/__init__.py
odoo/addons/l10n_ch_isr_payment_grouping/__manifest__.py
odoo/addons/l10n_ch_isr_payment_grouping/i18n/l10n_ch_isr_payment_grouping.pot
odoo/addons/l10n_ch_isr_payment_grouping/models/__init__.py
odoo/addons/l10n_ch_isr_payment_grouping/models/account_move.py
odoo/addons/l10n_ch_isr_payment_grouping/models/account_payment.py
odoo/addons/l10n_ch_isr_payment_grouping/models/res_bank.py
odoo/addons/l10n_ch_isr_payment_grouping/readme/CONTRIBUTORS.rst
odoo/addons/l10n_ch_isr_payment_grouping/readme/DESCRIPTION.rst
odoo/addons/l10n_ch_isr_payment_grouping/readme/INSTALL.rst
odoo/addons/l10n_ch_isr_payment_grouping/readme/USAGE.rst
odoo/addons/l10n_ch_isr_payment_grouping/static/description/icon.png
odoo/addons/l10n_ch_isr_payment_grouping/static/description/index.html
odoo/addons/l10n_ch_isr_payment_grouping/tests/__init__.py
odoo/addons/l10n_ch_isr_payment_grouping/tests/test_l10n_ch_payment_isr.py
odoo13_addon_l10n_ch_isr_payment_grouping-13.0.1.0.1.dev4.dist-info/METADATA
odoo13_addon_l10n_ch_isr_payment_grouping-13.0.1.0.1.dev4.dist-info/WHEEL
odoo13_addon_l10n_ch_isr_payment_grouping-13.0.1.0.1.dev4.dist-info/top_level.txt
odoo13_addon_l10n_ch_isr_payment_grouping-13.0.1.0.1.dev4.dist-info/RECORD
